array_api_typing/__init__.py
array_api_typing/typing_2024_12/__init__.py
array_api_typing/typing_2024_12/_api_constant.py
array_api_typing/typing_2024_12/_api_fft_typing.py
array_api_typing/typing_2024_12/_api_linalg_typing.py
array_api_typing/typing_2024_12/_api_return_typing.py
array_api_typing/typing_2024_12/_api_typing.py
array_api_typing/typing_2024_12/_array_typing.py
array_api_typing/typing_compat/__init__.py
array_api_typing/typing_compat/_api_typing.py
array_api_typing/typing_compat/_array_typing.py
array_api_typing/typing_extra/__init__.py
array_api_typing/typing_extra/_api_typing.py
array_api_typing/typing_extra/_at.py
xbarray/__init__.py
xbarray/jax.py
xbarray/numpy.py
xbarray/pytorch.py
xbarray/backends/_cls_base.py
xbarray/backends/base.py
xbarray/backends/jax.py
xbarray/backends/numpy.py
xbarray/backends/pytorch.py
xbarray/backends/_implementations/_common/implementations.py
xbarray/backends/_implementations/jax/__init__.py
xbarray/backends/_implementations/jax/_extra.py
xbarray/backends/_implementations/jax/_typing.py
xbarray/backends/_implementations/jax/random.py
xbarray/backends/_implementations/numpy/__init__.py
xbarray/backends/_implementations/numpy/_extra.py
xbarray/backends/_implementations/numpy/_typing.py
xbarray/backends/_implementations/numpy/random.py
xbarray/backends/_implementations/pytorch/__init__.py
xbarray/backends/_implementations/pytorch/_extra.py
xbarray/backends/_implementations/pytorch/_typing.py
xbarray/backends/_implementations/pytorch/random.py
xbarray/transformations/pointcloud/__init__.py
xbarray/transformations/pointcloud/base.py
xbarray/transformations/pointcloud/jax.py
xbarray/transformations/pointcloud/numpy.py
xbarray/transformations/pointcloud/pytorch.py
xbarray/transformations/rotation_conversions/__init__.py
xbarray/transformations/rotation_conversions/base.py
xbarray/transformations/rotation_conversions/jax.py
xbarray/transformations/rotation_conversions/numpy.py
xbarray-0.0.1a13.dist-info/licenses/LICENSE
xbarray-0.0.1a13.dist-info/METADATA
xbarray-0.0.1a13.dist-info/WHEEL
xbarray-0.0.1a13.dist-info/top_level.txt
xbarray-0.0.1a13.dist-info/RECORD
